{
    "w": {
        "lower": [
            0,
            0,
            150
        ],
        "upper": [
            179,
            80,
            255
        ]
    },
    "b": {
        "lower": [
            101,
            60,
            60
        ],
        "upper": [
            121,
            255,
            255
        ]
    },
    "y": {
        "lower": [
            23,
            60,
            60
        ],
        "upper": [
            43,
            255,
            255
        ]
    },
    "g": {
        "lower": [
            42,
            60,
            60
        ],
        "upper": [
            62,
            255,
            255
        ]
    },
    "o": {
        "lower": [
            0,
            60,
            60
        ],
        "upper": [
            10,
            255,
            255
        ]
    },
    "r": {
        "lower": [
            170,
            60,
            60
        ],
        "upper": [
            179,
            255,
            255
        ]
    }
}